deepsafety-0.1.0.dist-info/licenses/LICENSE
dispersion/__init__.py
dispersion/dense_gas.py
dispersion/neutrally_buoyant.py
dispersion/toxic_effects.py
dispersion/utils.py
fire_and_explosion/__init__.py
fire_and_explosion/explosion_characterization.py
fire_and_explosion/flammability.py
fire_and_explosion/ignition_sources.py
fire_and_explosion/utils.py
deepsafety-0.1.0.dist-info/METADATA
deepsafety-0.1.0.dist-info/WHEEL
deepsafety-0.1.0.dist-info/top_level.txt
deepsafety-0.1.0.dist-info/RECORD
