Metadata-Version: 2.4
Name: deepsafety
Version: 0.1.0
Summary: A Python library for industrial and safety calculations
Author-email: Pkbythebay29 <kannan@haztechrisk.org>
License: MIT License
Project-URL: Homepage, https://github.com/pkbythebay29/deepsafety
Keywords: process safety,dispersion,flammability,explosions,toxicology
Classifier: Programming Language :: Python :: 3
Classifier: License :: OSI Approved :: MIT License
Classifier: Operating System :: OS Independent
License-File: LICENSE
Dynamic: license-file
